{
    "2": [
        45,
        41,
        361,
        374,
        328,
        378,
        224
    ],
    "3": [
        261,
        182,
        125,
        50
    ],
    "7": [
        129,
        267,
        353,
        246,
        278,
        35,
        20,
        15,
        55
    ],
    "8": [
        178,
        89,
        367,
        183,
        54,
        61
    ],
    "9": [
        215
    ],
    "10": [
        248
    ],
    "11": [
        60,
        291,
        112,
        123
    ],
    "12": [
        86,
        373,
        211,
        345
    ],
    "15": [
        55,
        7,
        20,
        200,
        214
    ],
    "17": [
        174,
        333,
        347,
        220
    ],
    "18": [
        228,
        221,
        171,
        180,
        138,
        334,
        163,
        209,
        127,
        257
    ],
    "20": [
        15,
        7,
        35,
        298,
        294,
        200
    ],
    "21": [
        138,
        180,
        261,
        201,
        194
    ],
    "22": [
        222,
        345,
        92,
        292,
        259
    ],
    "23": [
        92,
        355,
        193,
        27,
        301,
        218
    ],
    "26": [
        271,
        294,
        298,
        266,
        183,
        367
    ],
    "27": [
        193,
        299,
        332,
        301,
        23
    ],
    "28": [
        120,
        259,
        247,
        329
    ],
    "29": [
        307,
        50
    ],
    "30": [
        311,
        368,
        224,
        378,
        180
    ],
    "35": [
        7,
        278,
        120,
        329,
        298,
        20
    ],
    "36": [
        331,
        38,
        248
    ],
    "38": [
        36,
        248
    ],
    "41": [
        45,
        361,
        2
    ],
    "45": [
        369,
        114,
        41,
        2,
        224,
        368
    ],
    "46": [
        215,
        112,
        362,
        123,
        328,
        140,
        131
    ],
    "48": [
        347,
        377,
        129,
        339,
        90
    ],
    "50": [
        307,
        29,
        201,
        261,
        3,
        125,
        86,
        345,
        338,
        308,
        167
    ],
    "53": [
        100,
        364,
        125
    ],
    "54": [
        8,
        183
    ],
    "55": [
        339,
        129,
        7,
        15,
        214,
        135
    ],
    "56": [
        248
    ],
    "57": [
        373,
        211
    ],
    "58": [
        336,
        381
    ],
    "60": [
        341,
        140,
        131,
        215,
        291,
        11,
        123,
        328,
        362
    ],
    "61": [
        178,
        8,
        248
    ],
    "63": [
        283,
        247,
        259,
        82,
        244,
        284
    ],
    "64": [
        161,
        67,
        217,
        331
    ],
    "65": [
        176,
        64,
        205,
        220,
        132,
        347,
        330
    ],
    "67": [
        80,
        330,
        344,
        217,
        64,
        161
    ],
    "68": [
        266,
        284,
        244,
        160,
        321,
        183
    ],
    "69": [
        244,
        218
    ],
    "70": [
        109,
        240,
        381,
        352,
        231,
        371
    ],
    "76": [
        127,
        188,
        333,
        174
    ],
    "80": [
        205,
        220,
        132,
        170,
        90,
        130,
        330,
        67,
        161
    ],
    "82": [
        259,
        292,
        92,
        244,
        63
    ],
    "86": [
        50,
        125,
        373,
        12,
        345
    ],
    "89": [
        331,
        367,
        8,
        178
    ],
    "90": [
        170,
        132,
        347,
        48,
        339,
        130,
        80
    ],
    "92": [
        292,
        22,
        345,
        211,
        373,
        109,
        371,
        355,
        23,
        218,
        244,
        82
    ],
    "99": [
        193,
        355,
        231,
        195,
        192,
        343,
        269,
        332,
        299
    ],
    "100": [
        359,
        113,
        112,
        215,
        364,
        53,
        125
    ],
    "102": [
        236,
        373
    ],
    "107": [
        163,
        194,
        307
    ],
    "109": [
        373,
        240,
        70,
        371,
        92
    ],
    "110": [
        333,
        188,
        163,
        307,
        326,
        377,
        216
    ],
    "112": [
        123,
        11,
        291,
        215,
        100,
        113
    ],
    "113": [
        123,
        112,
        100,
        359
    ],
    "114": [
        45,
        369,
        228
    ],
    "120": [
        288,
        278,
        222,
        259,
        28,
        329,
        35
    ],
    "121": [
        261,
        370,
        125,
        182
    ],
    "123": [
        328,
        362,
        60,
        11,
        112,
        113,
        359,
        262
    ],
    "125": [
        182,
        121,
        370,
        359,
        100,
        53,
        364,
        253,
        302,
        373,
        86,
        50,
        3
    ],
    "127": [
        257,
        18,
        209,
        163,
        188,
        76,
        174,
        220
    ],
    "129": [
        48,
        377,
        323,
        267,
        7,
        55,
        339
    ],
    "130": [
        80,
        90,
        339,
        135,
        330
    ],
    "131": [
        140,
        215,
        60
    ],
    "132": [
        220,
        347,
        90,
        170,
        80
    ],
    "135": [
        130,
        339,
        55,
        214,
        200,
        330
    ],
    "138": [
        18,
        171,
        180,
        21,
        194,
        334
    ],
    "140": [
        219,
        131,
        60,
        341,
        235,
        358
    ],
    "144": [
        54,
        8,
        183
    ],
    "149": [
        378,
        328,
        224,
        30,
        201,
        29,
        3
    ],
    "155": [
        344,
        330,
        200,
        367,
        176
    ],
    "159": [
        127,
        174,
        76,
        333,
        17,
        220
    ],
    "160": [
        68,
        244,
        321
    ],
    "161": [
        80,
        67,
        64,
        331
    ],
    "163": [
        127,
        18,
        334,
        194,
        107,
        307,
        110,
        188
    ],
    "167": [
        307,
        50,
        308,
        246
    ],
    "170": [
        132,
        90,
        80
    ],
    "171": [
        180,
        138,
        18
    ],
    "174": [
        127,
        76,
        333,
        17,
        220
    ],
    "176": [
        217,
        344,
        155,
        367,
        331
    ],
    "178": [
        331,
        89,
        8,
        61,
        248
    ],
    "180": [
        18,
        171,
        221,
        311,
        30,
        378,
        272,
        261,
        21,
        138
    ],
    "182": [
        261,
        121,
        125,
        3
    ],
    "183": [
        367,
        26,
        266,
        68,
        321,
        54,
        8
    ],
    "188": [
        76,
        127,
        163,
        110,
        333
    ],
    "192": [
        352,
        381,
        343,
        99,
        195
    ],
    "193": [
        355,
        99,
        299,
        27,
        23
    ],
    "194": [
        163,
        334,
        138,
        21,
        201,
        307,
        107
    ],
    "195": [
        231,
        352,
        192,
        99
    ],
    "200": [
        330,
        135,
        214,
        15,
        20,
        294,
        271,
        367,
        155
    ],
    "201": [
        21,
        261,
        50,
        307,
        194
    ],
    "205": [
        220,
        80
    ],
    "209": [
        18,
        127,
        257
    ],
    "211": [
        12,
        57,
        373,
        92,
        345
    ],
    "214": [
        135,
        55,
        15,
        200
    ],
    "215": [
        291,
        60,
        131,
        9,
        253,
        364,
        100,
        112
    ],
    "216": [
        333,
        110,
        377,
        347
    ],
    "217": [
        64,
        67,
        344,
        176,
        331
    ],
    "218": [
        244,
        92,
        23,
        69
    ],
    "219": [
        140,
        358,
        361
    ],
    "220": [
        127,
        174,
        17,
        347,
        132,
        80,
        205
    ],
    "221": [
        228,
        368,
        311,
        180,
        18
    ],
    "222": [
        223,
        338,
        345,
        22,
        259,
        120,
        288
    ],
    "223": [
        246,
        308,
        338,
        222,
        288,
        278
    ],
    "224": [
        368,
        45,
        2,
        378,
        30
    ],
    "228": [
        237,
        114,
        369,
        368,
        221,
        18
    ],
    "231": [
        371,
        70,
        352,
        195,
        99,
        355
    ],
    "235": [
        361,
        358,
        140,
        341
    ],
    "236": [
        102,
        373
    ],
    "237": [
        228
    ],
    "240": [
        373,
        310,
        336,
        381,
        70,
        109
    ],
    "241": [
        307,
        267,
        323,
        377
    ],
    "244": [
        68,
        284,
        63,
        82,
        92,
        218,
        69,
        160
    ],
    "246": [
        353,
        307,
        167,
        308,
        223,
        278,
        7
    ],
    "247": [
        329,
        28,
        259,
        63,
        283
    ],
    "248": [
        36,
        38,
        331,
        178,
        61,
        10,
        56
    ],
    "253": [
        364,
        215,
        302,
        125
    ],
    "257": [
        18,
        209,
        127
    ],
    "259": [
        120,
        222,
        22,
        292,
        82,
        63,
        247,
        28
    ],
    "260": [
        332,
        269,
        301
    ],
    "261": [
        21,
        180,
        272,
        378,
        328,
        370,
        121,
        182,
        3,
        50,
        307,
        201
    ],
    "262": [
        328,
        123,
        359,
        370
    ],
    "266": [
        26,
        298,
        306,
        283,
        284,
        68,
        183
    ],
    "267": [
        323,
        241,
        307,
        353,
        7,
        129
    ],
    "269": [
        332,
        99,
        301,
        260
    ],
    "271": [
        200,
        294,
        26,
        367
    ],
    "272": [
        180,
        261
    ],
    "274": [
        362,
        11,
        291,
        140
    ],
    "278": [
        7,
        246,
        223,
        120,
        288,
        35
    ],
    "283": [
        306,
        329,
        247,
        63,
        284,
        266
    ],
    "284": [
        266,
        283,
        63,
        244,
        68
    ],
    "288": [
        278,
        223,
        222,
        120
    ],
    "289": [
        294,
        306,
        35,
        283,
        329,
        288,
        26
    ],
    "291": [
        11,
        60,
        215,
        112
    ],
    "292": [
        259,
        22,
        92,
        82
    ],
    "294": [
        200,
        20,
        298,
        26,
        271
    ],
    "298": [
        294,
        20,
        35,
        329,
        306,
        266,
        26
    ],
    "299": [
        193,
        99,
        332,
        27
    ],
    "301": [
        23,
        27,
        332,
        260,
        269
    ],
    "302": [
        253,
        373,
        125
    ],
    "304": [
        272,
        149,
        378,
        311,
        370,
        262,
        328
    ],
    "306": [
        329,
        283,
        266,
        298
    ],
    "307": [
        110,
        163,
        107,
        194,
        201,
        261,
        29,
        50,
        167,
        246,
        353,
        267,
        241,
        377,
        326
    ],
    "308": [
        167,
        50,
        338,
        223,
        246
    ],
    "310": [
        373,
        336,
        240
    ],
    "311": [
        221,
        368,
        30,
        180
    ],
    "321": [
        183,
        68,
        160
    ],
    "323": [
        377,
        241,
        267,
        129
    ],
    "326": [
        110,
        307,
        377
    ],
    "328": [
        378,
        2,
        374,
        341,
        362,
        60,
        123,
        262,
        370,
        261
    ],
    "329": [
        35,
        120,
        28,
        247,
        283,
        306,
        298
    ],
    "330": [
        80,
        130,
        135,
        200,
        155,
        344,
        67
    ],
    "331": [
        161,
        64,
        217,
        176,
        367,
        89,
        178,
        248,
        36
    ],
    "332": [
        27,
        299,
        99,
        269,
        260,
        301
    ],
    "333": [
        17,
        174,
        76,
        188,
        110,
        216,
        347
    ],
    "334": [
        18,
        138,
        194,
        163
    ],
    "336": [
        310,
        58,
        381,
        240
    ],
    "337": [
        110,
        347,
        216,
        333,
        48,
        323
    ],
    "338": [
        308,
        50,
        345,
        222,
        223
    ],
    "339": [
        90,
        48,
        129,
        55,
        135,
        130
    ],
    "341": [
        361,
        235,
        358,
        140,
        60,
        328,
        374
    ],
    "343": [
        192,
        99
    ],
    "344": [
        67,
        330,
        155,
        176,
        217
    ],
    "345": [
        338,
        50,
        86,
        12,
        211,
        92,
        22,
        222
    ],
    "347": [
        220,
        17,
        333,
        216,
        377,
        48,
        90,
        132
    ],
    "352": [
        70,
        381,
        192,
        195,
        231
    ],
    "353": [
        307,
        246,
        7,
        267
    ],
    "355": [
        92,
        371,
        231,
        99,
        193,
        23
    ],
    "358": [
        361,
        219,
        140,
        341,
        235
    ],
    "359": [
        262,
        123,
        113,
        100,
        125,
        370
    ],
    "361": [
        41,
        219,
        358,
        235,
        341,
        374,
        2
    ],
    "362": [
        60,
        123,
        328
    ],
    "364": [
        100,
        215,
        253,
        125,
        53
    ],
    "367": [
        176,
        155,
        200,
        271,
        26,
        183,
        8,
        89,
        331
    ],
    "368": [
        228,
        369,
        45,
        224,
        30,
        311,
        221
    ],
    "369": [
        228,
        114,
        45,
        368
    ],
    "370": [
        328,
        262,
        359,
        125,
        121,
        261
    ],
    "371": [
        92,
        109,
        70,
        231,
        355
    ],
    "373": [
        86,
        125,
        302,
        236,
        102,
        310,
        240,
        109,
        92,
        211,
        57,
        12
    ],
    "374": [
        2,
        361,
        341,
        328
    ],
    "377": [
        216,
        110,
        326,
        307,
        241,
        323,
        129,
        48,
        347
    ],
    "378": [
        30,
        224,
        2,
        328,
        261,
        180
    ],
    "381": [
        70,
        240,
        336,
        58,
        192,
        352
    ]
}